README.md
setup.py
fliton_fib_py/__init__.py
fliton_fib_py/version.py
fliton_fib_py.egg-info/PKG-INFO
fliton_fib_py.egg-info/SOURCES.txt
fliton_fib_py.egg-info/dependency_links.txt
fliton_fib_py.egg-info/entry_points.txt
fliton_fib_py.egg-info/requires.txt
fliton_fib_py.egg-info/top_level.txt
fliton_fib_py/cmd/__init__.py
fliton_fib_py/cmd/fib_numb.py
fliton_fib_py/fib_calcs/__init__.py
fliton_fib_py/fib_calcs/fib_number.py
fliton_fib_py/fib_calcs/fib_numbers.py
tests/fliton_fib_py/__init__.py
tests/fliton_fib_py/fib_calcs/__init__.py
tests/fliton_fib_py/fib_calcs/test_fib_number.py
tests/fliton_fib_py/fib_calcs/test_fib_numbers.py