Metadata-Version: 2.1
Name: fliton-fib-py
Version: 0.0.2
Summary: Calculate Fibonacci number series
Home-page: https://github.com/AdamW666/fliton-fib-py
Author: Adam Wong
Author-email: wizzardcloud@gmail.com
License: UNKNOWN
Platform: UNKNOWN
Classifier: Development Status :: 4 - Beta
Classifier: Programming Language :: Python :: 3
Classifier: Operating System :: OS Independent
Requires-Python: >=3
